text_transformer_example/__init__.py
text_transformer_example/core.py
text_transformer_example-0.1.0.dist-info/LICENSE
text_transformer_example-0.1.0.dist-info/METADATA
text_transformer_example-0.1.0.dist-info/WHEEL
text_transformer_example-0.1.0.dist-info/top_level.txt
text_transformer_example-0.1.0.dist-info/RECORD
